testpad_cli/__init__.py
testpad_cli-0.1.0.dist-info/METADATA
testpad_cli-0.1.0.dist-info/WHEEL
testpad_cli-0.1.0.dist-info/RECORD
